{
	"name": "Order_details",
	"properties": {
		"linkedServiceName": {
			"referenceName": "db_pizza",
			"type": "LinkedServiceReference"
		},
		"folder": {
			"name": "DB"
		},
		"annotations": [],
		"type": "AzureSqlTable",
		"schema": [
			{
				"name": "order_details_id",
				"type": "int",
				"precision": 10
			},
			{
				"name": "order_id",
				"type": "int",
				"precision": 10
			},
			{
				"name": "date",
				"type": "date"
			},
			{
				"name": "time",
				"type": "time",
				"scale": 7
			},
			{
				"name": "pizza_id",
				"type": "varchar"
			},
			{
				"name": "pizza_type_id",
				"type": "varchar"
			},
			{
				"name": "pizza_name",
				"type": "varchar"
			},
			{
				"name": "category",
				"type": "varchar"
			},
			{
				"name": "size",
				"type": "char"
			},
			{
				"name": "price",
				"type": "decimal",
				"precision": 6,
				"scale": 2
			},
			{
				"name": "quantity",
				"type": "int",
				"precision": 10
			},
			{
				"name": "total_price",
				"type": "decimal",
				"precision": 10,
				"scale": 2
			}
		],
		"typeProperties": {
			"schema": "dbo",
			"table": "order_details"
		}
	}
}